tarzan/__init__.py
tarzan/info.py
tarzan/utils.py
tarzan/features/__init__.py
tarzan/features/audio.py
tarzan/features/features.py
tarzan/features/json.py
tarzan/features/scalar.py
tarzan/features/sequence.py
tarzan/features/tensor.py
tarzan/features/text.py
tarzan/readers/__init__.py
tarzan/readers/tar_reader.py
tarzan/writers/__init__.py
tarzan/writers/base_writer.py
tarzan/writers/shard_writer.py
tarzan/writers/tar_writer.py
tarzan-0.1.0.dist-info/METADATA
tarzan-0.1.0.dist-info/WHEEL
tarzan-0.1.0.dist-info/RECORD
