Metadata-Version: 2.1
Name: tarzan
Version: 0.1.0
Summary: high-level IO for tar based dataset
Author-email: Yuchao Zhang <418121364@qq.com>
Keywords: datasets,tar
Requires-Python: >=3.8
Requires-Dist: dill~=0.3.7
Requires-Dist: librosa~=0.10.1
Requires-Dist: more-itertools~=10.2.0
Requires-Dist: numpy~=1.0
Requires-Dist: soundfile~=0.12.1
Provides-Extra: dev
Requires-Dist: black; extra == 'dev'
Requires-Dist: flake8; extra == 'dev'
Requires-Dist: flake8-bugbear; extra == 'dev'
Requires-Dist: flake8-comprehensions; extra == 'dev'
Requires-Dist: flake8-print; extra == 'dev'
Requires-Dist: isort; extra == 'dev'
Requires-Dist: mypy; extra == 'dev'
Requires-Dist: pep8-naming; extra == 'dev'
Provides-Extra: test
Requires-Dist: pytest; extra == 'test'
